filesystem/__init__.py
filesystem/__core__/__init__.py
filesystem/compression/__init__.py
filesystem/console/__init__.py
filesystem/console/ansi.py
filesystem/console/ansitowin32.py
filesystem/console/initialise.py
filesystem/console/win32.py
filesystem/console/winterm.py
filesystem/console/tests/__init__.py
filesystem/console/tests/ansi_test.py
filesystem/console/tests/ansitowin32_test.py
filesystem/console/tests/console_test.py
filesystem/console/tests/initialise_test.py
filesystem/console/tests/isatty_test.py
filesystem/console/tests/utils.py
filesystem/console/tests/winterm_test.py
filesystem/device/__init__.py
filesystem/device/cpu/__init__.py
filesystem/device/disks/__init__.py
filesystem/device/memory/__init__.py
filesystem/device/network/__init__.py
filesystem/directory/__init__.py
filesystem/file/__init__.py
filesystem/watcher/__init__.py
filesystem/wrapper/__init__.py
filesystempro-3.0.0.0.dist-info/LICENSE
filesystempro-3.0.0.0.dist-info/METADATA
filesystempro-3.0.0.0.dist-info/WHEEL
filesystempro-3.0.0.0.dist-info/top_level.txt
filesystempro-3.0.0.0.dist-info/RECORD
