Metadata-Version: 2.1
Name: filesystempro
Version: 3.0.0.0
Summary: FileSystemPro is a powerful toolkit designed to handle file and directory operations with ease and efficiency across various operating systems.
Home-page: https://github.com/hbisneto/FileSystemPro
Author: Heitor Bisneto
Author-email: heitor.bardemaker@live.com
License: MIT License
Project-URL: Homepage, https://github.com/hbisneto/FileSystemPro
Project-URL: Repository, https://github.com/hbisneto/FileSystemPro.git
Keywords: filesystem,file-operations,directory-management,cross-platform,file-io,pathlib-wrapper,compression-utils,file-watcher,os-agnostic,linux,macos,windows
Platform: any
Classifier: Development Status :: 5 - Production/Stable
Classifier: Intended Audience :: Developers
Classifier: Intended Audience :: Education
Classifier: Intended Audience :: Science/Research
Classifier: Intended Audience :: End Users/Desktop
Classifier: Topic :: Software Development :: Libraries
Classifier: License :: OSI Approved :: MIT License
Classifier: Operating System :: POSIX :: Linux
Classifier: Operating System :: MacOS :: MacOS X
Classifier: Operating System :: Microsoft :: Windows
Classifier: Programming Language :: Python :: 3.10
Classifier: Programming Language :: Python :: 3.11
Classifier: Programming Language :: Python :: 3.12
Classifier: Programming Language :: Python :: 3.13
Classifier: Programming Language :: Python :: 3.14
Requires-Python: >=3.10
Requires-Dist: requests
